Workbook

Sheet Assumptions
A1: HERAKLEITOS — BUDGET ASSUMPTIONS
A2: The next model: production pipeline + gate ablation. Prices verified 2026-07-22. Edit yellow cells.
A4: UNIT PRICES | E4: Source
A5: DeepSeek-V3.1 — input | B5: 0.6 | C5: $/M tok | E5: Together AI, verified 2026-07-22
A6: DeepSeek-V3.1 — output | B6: 1.7 | C6: $/M tok | E6: Together AI, verified 2026-07-22
A7: Qwen3-235B — input | B7: 0.2 | C7: $/M tok | E7: Together AI, verified 2026-07-22
A8: Qwen3-235B — output | B8: 0.6 | C8: $/M tok | E8: Together AI, verified 2026-07-22
A9: Frontier judge — input (blended) | B9: 12 | C9: $/M tok | E9: Claude Opus + GPT-5 class, approx.
A10: Frontier judge — output (blended) | B10: 50 | C10: $/M tok | E10: Claude Opus + GPT-5 class, approx.
A11: H100 GPU rental | B11: 2.5 | C11: $/hr | E11: RunPod/Lambda on-demand, 2026 (spot ~$1.20)
A12: Expert rater (classicist/philosopher) | B12: 100 | C12: $/hr | E12: estimate
A13: Domain herakleitos.ai | B13: 75 | C13: $/yr | E13: .ai registrar, estimate
A15: TOKEN SIZES (per call)
A16: Teacher generation — input tokens | B16: 300
A17: Teacher generation — output tokens | B17: 400
A18: Judge rubric call — input tokens | B18: 700
A19: Judge rubric call — output tokens | B19: 150
A20: Runtime-grader score — input tokens | B20: 900
A21: Runtime-grader score — output tokens | B21: 200
A22: Frontier call — input tokens | B22: 1500
A23: Frontier call — output tokens | B23: 200
A25: CONTINGENCY
A26: Contingency (retries, price drift, flywheel) | B26: 0.25
A28: PER-TIER VOLUMES | B28: Lean | C28: Recommended | D28: Comprehensive
A29: Candidates generated | B29: 8000 | C29: 26000 | D29: 78000
A30: Gate rubric calls / candidate | B30: 3 | C30: 3 | D30: 3
A31: Target acceptance rate | B31: 0.79 | C31: 0.79 | D31: 0.79
A32: LoRA training runs | B32: 4 | C32: 6 | D32: 12
A33: GPU hrs / LoRA run (0 = local Mac) | B33: 0 | C33: 4 | D33: 6
A34: Full fine-tune runs | B34: 0 | C34: 2 | D34: 4
A35: GPU hrs / full-FT run | B35: 0 | C35: 10 | D35: 14
A36: Frontier calibration calls | B36: 1200 | C36: 1200 | D36: 2400
A37: Frontier report-card calls | B37: 400 | C37: 1600 | D37: 3200
A38: Runtime-grader scoring calls | B38: 0 | C38: 26000 | D38: 78000
A39: Imitation regen (M tokens) | B39: 1 | C39: 2 | D39: 4
A40: Expert rater hours | B40: 0 | C40: 0 | D40: 40
A41: Domain years | B41: 1 | C41: 1 | D41: 1
A42: → Accepted training examples (derived) | B42: =B29*B31 | C42: =C29*C31 | D42: =D29*D31
A44: Yellow = editable lever. Blue = hardcoded input. Change any and the Budget tab recomputes.

Sheet Budget
A1: HERAKLEITOS — BUDGET, THE NEXT MODEL
A2: Three scope tiers. All figures computed from the Assumptions tab.
A4: LINE ITEM | B4: Lean | C4: Recommended | D4: Comprehensive
A6: PHASE 2 — DATA GENERATION (open-weights, Together)
A7: Teacher generation (DeepSeek-V3.1) | B7: =Assumptions!$B$29*(Assumptions!$B$16*Assumptions!$B$5+Assumptions!$B$17*Assumptions!$B$6)/1000000 | C7: =Assumptions!$C$29*(Assumptions!$B$16*Assumptions!$B$5+Assumptions!$B$17*Assumptions!$B$6)/1000000 | D7: =Assumptions!$D$29*(Assumptions!$B$16*Assumptions!$B$5+Assumptions!$B$17*Assumptions!$B$6)/1000000
A8: Eval-gate judging (Qwen3-235B × rubrics) | B8: =Assumptions!$B$29*Assumptions!$B$30*(Assumptions!$B$18*Assumptions!$B$7+Assumptions!$B$19*Assumptions!$B$8)/1000000 | C8: =Assumptions!$C$29*Assumptions!$C$30*(Assumptions!$B$18*Assumptions!$B$7+Assumptions!$B$19*Assumptions!$B$8)/1000000 | D8: =Assumptions!$D$29*Assumptions!$D$30*(Assumptions!$B$18*Assumptions!$B$7+Assumptions!$B$19*Assumptions!$B$8)/1000000
A9: Imitation-tier regeneration | B9: =Assumptions!$B$39*((Assumptions!$B$5+Assumptions!$B$6)/2) | C9: =Assumptions!$C$39*((Assumptions!$B$5+Assumptions!$B$6)/2) | D9: =Assumptions!$D$39*((Assumptions!$B$5+Assumptions!$B$6)/2)
A10: Runtime-grader scoring data | B10: =Assumptions!$B$38*(Assumptions!$B$20*Assumptions!$B$7+Assumptions!$B$21*Assumptions!$B$8)/1000000 | C10: =Assumptions!$C$38*(Assumptions!$B$20*Assumptions!$B$7+Assumptions!$B$21*Assumptions!$B$8)/1000000 | D10: =Assumptions!$D$38*(Assumptions!$B$20*Assumptions!$B$7+Assumptions!$B$21*Assumptions!$B$8)/1000000
A12: PHASE 3 — TRAINING (the gate ablation)
A13: LoRA runs (filtered vs unfiltered × seeds) | B13: =Assumptions!$B$32*Assumptions!$B$33*Assumptions!$B$11 | C13: =Assumptions!$C$32*Assumptions!$C$33*Assumptions!$B$11 | D13: =Assumptions!$D$32*Assumptions!$D$33*Assumptions!$B$11
A14: Full fine-tune confirmation runs | B14: =Assumptions!$B$34*Assumptions!$B$35*Assumptions!$B$11 | C14: =Assumptions!$C$34*Assumptions!$C$35*Assumptions!$B$11 | D14: =Assumptions!$D$34*Assumptions!$D$35*Assumptions!$B$11
A16: PHASE 1 — FRONTIER EVALUATION (offline grading only)
A17: Cross-judge calibration (2 providers) | B17: =Assumptions!$B$36*(Assumptions!$B$22*Assumptions!$B$9+Assumptions!$B$23*Assumptions!$B$10)/1000000 | C17: =Assumptions!$C$36*(Assumptions!$B$22*Assumptions!$B$9+Assumptions!$B$23*Assumptions!$B$10)/1000000 | D17: =Assumptions!$D$36*(Assumptions!$B$22*Assumptions!$B$9+Assumptions!$B$23*Assumptions!$B$10)/1000000
A18: Report cards across ablation arms | B18: =Assumptions!$B$37*(Assumptions!$B$22*Assumptions!$B$9+Assumptions!$B$23*Assumptions!$B$10)/1000000 | C18: =Assumptions!$C$37*(Assumptions!$B$22*Assumptions!$B$9+Assumptions!$B$23*Assumptions!$B$10)/1000000 | D18: =Assumptions!$D$37*(Assumptions!$B$22*Assumptions!$B$9+Assumptions!$B$23*Assumptions!$B$10)/1000000
A20: VALIDATION & MISC
A21: Expert human raters (judge↔human agreement) | B21: =Assumptions!$B$40*Assumptions!$B$12 | C21: =Assumptions!$C$40*Assumptions!$B$12 | D21: =Assumptions!$D$40*Assumptions!$B$12
A22: Domain (herakleitos.ai) | B22: =Assumptions!$B$41*Assumptions!$B$13 | C22: =Assumptions!$C$41*Assumptions!$B$13 | D22: =Assumptions!$D$41*Assumptions!$B$13
A24: SUBTOTAL | B24: =B7+B8+B9+B10+B13+B14+B17+B18+B21+B22 | C24: =C7+C8+C9+C10+C13+C14+C17+C18+C21+C22 | D24: =D7+D8+D9+D10+D13+D14+D17+D18+D21+D22
A25: Contingency | B25: =B24*Assumptions!$B$26 | C25: =C24*Assumptions!$B$26 | D25: =D24*Assumptions!$B$26
A26: TOTAL (cash, no credits) | B26: =B24+B25 | C26: =C24+C25 | D26: =D24+D25
A28: POTENTIAL FUNDING OFFSETS (if credits awarded — see MODELS.md / application kit)
A29: Together research credits (API, cap $500) | B29: =-MIN(B7+B8+B9+B10,500) | C29: =-MIN(C7+C8+C9+C10,500) | D29: =-MIN(D7+D8+D9+D10,500)
A30: OpenAI/Anthropic researcher credits (frontier) | B30: =-MIN(B17+B18,1000) | C30: =-MIN(C17+C18,1000) | D30: =-MIN(D17+D18,1000)
A31: TPU Research Cloud / spot GPU (training) | B31: =-B13+B14 | C31: =-C13+C14 | D31: =-D13+D14
A32: NET CASH (best case, all credits awarded) | B32: =B26+B29+B30+B31 | C32: =C26+C29+C30+C31 | D32: =D26+D29+D30+D31
A34: WHAT EACH TIER BUYS
A35: Lean (~prove the ablation): 8k candidates, student trained LOCALLY on the Mac (LoRA, $0 GPU),
A36: calibration + a light frontier pass. Nearly free if you already own the domain.
A37: Recommended (workshop-paper grade): production 26k→~20k dataset, 7-8B student, the full
A38: filtered-vs-unfiltered ablation across seeds, frontier calibration + report cards on every arm.
A39: Comprehensive (conference grade): 3 flywheel generations + expert human raters validating that
A40: the judge tracks human judgment + a classicist verifying the corpus. Raters are the big line.
A42: The claim that makes this a contribution: 'the gate — not raw distillation — transmits the style.'
A43: That is the filtered-vs-unfiltered arm. Spend the money there before spending it on a bigger model.
